bp_tokenizer/__init__.py
bp_tokenizer/tokenizer.py
bp_tokenizer/vocab.json
bp_tokenizer-1.0.2.dist-info/licenses/LICENSE
bp_tokenizer-1.0.2.dist-info/METADATA
bp_tokenizer-1.0.2.dist-info/WHEEL
bp_tokenizer-1.0.2.dist-info/top_level.txt
bp_tokenizer-1.0.2.dist-info/RECORD
