Metadata-Version: 2.4
Name: bp_tokenizer
Version: 1.0.2
Summary: A high-performance Python tokenizer using Byte-Pair Encoding (BPE) with 100k vocabulary, supporting text encoding, decoding, and normalization for NLP applications.
Author-email: Md Mohsin <siam.mohsin2005@gmail.com>
License: MIT
Project-URL: Repository, https://github.com/mdmohsin212/bpe_tokenizer
Keywords: tokenizer,BPE,NLP,text-processing,vocabulary
Classifier: Programming Language :: Python :: 3
Classifier: Operating System :: OS Independent
Classifier: Topic :: Text Processing :: Linguistic
Requires-Python: >=3.9
License-File: LICENSE
Dynamic: license-file
